mede/__init__.py
mede/dataset.py
mede/deidentify.py
mede/dicom_deidentification.py
mede/dicom_skullstrip_defacing.py
mede/model.py
mede/text_detection.py
mede/twix_deidentification.py
mede/wsi_deidentification.py
mede/dicom_deid/attributes.json
mede/dicom_deid/confidentiality_profile_attributes.json
mede/dicom_deid/deid_options/basicProfile.dicom
mede/dicom_deid/deid_options/cleanDescOpt.dicom
mede/dicom_deid/deid_options/cleanGraphOpt.dicom
mede/dicom_deid/deid_options/cleanStructContOpt.dicom
mede/dicom_deid/deid_options/rtnDevIdOpt.dicom
mede/dicom_deid/deid_options/rtnInstIdOpt.dicom
mede/dicom_deid/deid_options/rtnLongFullDatesOpt.dicom
mede/dicom_deid/deid_options/rtnLongModifDatesOpt.dicom
mede/dicom_deid/deid_options/rtnPatCharsOpt.dicom
mede/dicom_deid/deid_options/rtnSafePrivOpt.dicom
mede/dicom_deid/deid_options/rtnUIDsOpt.dicom
mede/mednext/MedNextV1.py
mede/mednext/__init__.py
mede/mednext/blocks.py
mede/models/__init__.py
mede/models/mednext_deface.pth
mede/models/mednext_skullstrip.pth
mede/utils/__init__.py
mede/utils/losses.py
mede/utils/utilities.py
mede/utils/validation.py
mede-0.0.5.dist-info/METADATA
mede-0.0.5.dist-info/WHEEL
mede-0.0.5.dist-info/entry_points.txt
mede-0.0.5.dist-info/licenses/LICENSE
mede-0.0.5.dist-info/RECORD
