Metadata-Version: 2.4
Name: mede
Version: 0.0.5
Summary: De-Identification of Medical Imaging Data: A Comprehensive Tool for Ensuring Patient Privacy
Project-URL: Homepage, https://github.com/TIO-IKIM/medical_image_deidentification
Project-URL: Issues, https://github.com/TIO-IKIM/medical_image_deidentification/issues
Author-email: Moritz Rempe & Lukas Heine <moritz.rempe@uk-essen.de>
License-Expression: MIT
License-File: LICENSE
Classifier: Development Status :: 4 - Beta
Classifier: Operating System :: OS Independent
Classifier: Programming Language :: Python :: 3
Requires-Python: >=3.9
Requires-Dist: deid
Requires-Dist: nibabel
Requires-Dist: numpy==1.26.4
Requires-Dist: opencv-python-headless
Requires-Dist: pandas
Requires-Dist: pillow
Requires-Dist: pydicom==2.3.1
Requires-Dist: pytesseract
Requires-Dist: pyyaml
Requires-Dist: safetensors==0.5.3
Requires-Dist: scikit-image
Requires-Dist: timm==1.0.7
Requires-Dist: torch==2.2.2
Requires-Dist: torchio
Requires-Dist: torchvision
Requires-Dist: tqdm
